wyzecam/__init__.py
wyzecam/api.py
wyzecam/api_models.py
wyzecam/iotc.py
wyzecam/mock/__init__.py
wyzecam/mock/mock_tutk_library.py
wyzecam/py.typed
wyzecam/tutk/__init__.py
wyzecam/tutk/device_config.json
wyzecam/tutk/tutk.py
wyzecam/tutk/tutk_ioctl_mux.py
wyzecam/tutk/tutk_protocol.py
wyzecam-1.2.0.dist-info/LICENSE
wyzecam-1.2.0.dist-info/WHEEL
wyzecam-1.2.0.dist-info/METADATA
wyzecam-1.2.0.dist-info/RECORD
