Metadata-Version: 2.1
Name: wyzecam
Version: 1.2.0
Summary: Python package for communicating with wyze cameras over the local network
Home-page: https://github.com/kroo/wyzecam
License: MIT
Author: kroo
Author-email: elliot@kroo.net
Requires-Python: >=3.8,<4.0
Classifier: Development Status :: 4 - Beta
Classifier: Intended Audience :: Developers
Classifier: License :: OSI Approved :: MIT License
Classifier: Operating System :: OS Independent
Classifier: Programming Language :: Python :: 3
Classifier: Programming Language :: Python :: 3.8
Classifier: Programming Language :: Python :: 3.9
Classifier: Topic :: Communications :: Chat
Classifier: Topic :: Home Automation
Classifier: Topic :: Software Development :: Libraries :: Python Modules
Requires-Dist: importlib_metadata (>=1.6.0,<2.0.0); python_version < "3.8"
Requires-Dist: pydantic (>=1.8.1,<2.0.0)
Requires-Dist: xxtea (>=2.0.0.post0,<3.0.0)
Project-URL: Repository, https://github.com/kroo/wyzecam
